simpleconf/__init__.py
simpleconf/caster.py
simpleconf/config.py
simpleconf/exceptions.py
simpleconf/loaders/__init__.py
simpleconf/loaders/dict.py
simpleconf/loaders/env.py
simpleconf/loaders/ini.py
simpleconf/loaders/json.py
simpleconf/loaders/osenv.py
simpleconf/loaders/toml.py
simpleconf/loaders/yaml.py
simpleconf/py.typed
simpleconf/utils.py
python_simpleconf-0.8.2.dist-info/METADATA
python_simpleconf-0.8.2.dist-info/WHEEL
python_simpleconf-0.8.2.dist-info/licenses/LICENSE
python_simpleconf-0.8.2.dist-info/RECORD
