Metadata-Version: 2.4
Name: python-simpleconf
Version: 0.8.2
Summary: Simple configuration management with python.
License: MIT
License-File: LICENSE
Author: pwwang
Author-email: pwwang@pwwang.com
Requires-Python: >=3.9,<4.0
Classifier: License :: OSI Approved :: MIT License
Classifier: Programming Language :: Python :: 3
Classifier: Programming Language :: Python :: 3.9
Classifier: Programming Language :: Python :: 3.10
Classifier: Programming Language :: Python :: 3.11
Classifier: Programming Language :: Python :: 3.12
Classifier: Programming Language :: Python :: 3.13
Classifier: Programming Language :: Python :: 3.14
Provides-Extra: all
Provides-Extra: async
Provides-Extra: env
Provides-Extra: ini
Provides-Extra: toml
Provides-Extra: yaml
Requires-Dist: aiofiles (>=23.0.0) ; extra == "async"
Requires-Dist: diot (>=0.3.2,<0.4.0)
Requires-Dist: iniconfig (>=2.0,<3.0) ; extra == "ini" or extra == "all"
Requires-Dist: panpath (>=0.4.8,<0.5.0)
Requires-Dist: python-dotenv (>=1.1,<2.0) ; extra == "env" or extra == "all"
Requires-Dist: pyyaml (>=6,<7) ; extra == "yaml" or extra == "all"
Requires-Dist: rtoml (>=0.12,<0.13) ; (sys_platform == "linux") and (extra == "toml" or extra == "all")
Requires-Dist: tomli (>=2.0,<3.0) ; (sys_platform != "linux") and (extra == "toml" or extra == "all")
Project-URL: Homepage, https://github.com/pwwang/simpleconf
Project-URL: Repository, https://github.com/pwwang/simpleconf
